Workbook

Sheet Vendor Master
A1: ABC Trading Pvt. Ltd.
A2: Procure-to-Pay (P2P) Portfolio
A3: Vendor, purchase order, invoice, payment and AP ageing workflow
A5: Vendor ID | B5: Vendor Name | C5: Vendor Type | D5: Payment Terms | E5: Bank Status
A6: V001 | B6: Office Supplies Co. | C6: Office Supplies | D6: 30 Days | E6: Verified
A7: V002 | B7: Tech Hardware Ltd. | C7: IT Equipment | D7: 45 Days | E7: Verified
A8: V003 | B8: Logistics Partner | C8: Logistics | D8: 30 Days | E8: Verified
A9: V004 | B9: Facility Services | C9: Facilities | D9: 30 Days | E9: Verified
A10: V005 | B10: Marketing Solutions | C10: Marketing | D10: 45 Days | E10: Pending Review

Sheet Purchase Orders
A1: ABC Trading Pvt. Ltd.
A2: Purchase Orders
A5: PO No. | B5: PO Date | C5: Vendor ID | D5: Vendor Name | E5: Description | F5: Quantity | G5: Unit Price | H5: PO Value | I5: Status
A6: PO-001 | B6: 2026-01-05 | C6: V001 | D6: =INDEX('Vendor Master'!B6:B10,MATCH(C6,'Vendor Master'!A6:A10,0)) | E6: Office Supplies | F6: 20 | G6: 1000 | H6: =F6*G6 | I6: Received
A7: PO-002 | B7: 2026-01-15 | C7: V002 | D7: =INDEX('Vendor Master'!B6:B10,MATCH(C7,'Vendor Master'!A6:A10,0)) | E7: Laptops | F7: 5 | G7: 30000 | H7: =F7*G7 | I7: Received
A8: PO-003 | B8: 2026-02-10 | C8: V003 | D8: =INDEX('Vendor Master'!B6:B10,MATCH(C8,'Vendor Master'!A6:A10,0)) | E8: Freight Services | F8: 1 | G8: 15000 | H8: =F8*G8 | I8: Received
A9: PO-004 | B9: 2026-02-20 | C9: V004 | D9: =INDEX('Vendor Master'!B6:B10,MATCH(C9,'Vendor Master'!A6:A10,0)) | E9: Facility Maintenance | F9: 1 | G9: 25000 | H9: =F9*G9 | I9: Received
A10: PO-005 | B10: 2026-03-05 | C10: V005 | D10: =INDEX('Vendor Master'!B6:B10,MATCH(C10,'Vendor Master'!A6:A10,0)) | E10: Marketing Services | F10: 1 | G10: 20000 | H10: =F10*G10 | I10: Pending Approval

Sheet AP Invoice Register
A1: ABC Trading Pvt. Ltd.
A2: AP Invoice Register
A5: Invoice No. | B5: Invoice Date | C5: PO No. | D5: Vendor ID | E5: Vendor Name | F5: Invoice Amount | G5: Due Date | H5: Amount Paid | I5: Outstanding | J5: Status
A6: PINV-001 | B6: 2026-01-12 | C6: PO-001 | D6: V001 | E6: =INDEX('Vendor Master'!B6:B10,MATCH(D6,'Vendor Master'!A6:A10,0)) | F6: 20000 | G6: 2026-02-11 | H6: 20000 | I6: =F6-H6 | J6: Paid
A7: PINV-002 | B7: 2026-01-22 | C7: PO-002 | D7: V002 | E7: =INDEX('Vendor Master'!B6:B10,MATCH(D7,'Vendor Master'!A6:A10,0)) | F7: 150000 | G7: 2026-03-08 | H7: 100000 | I7: =F7-H7 | J7: Partially Paid
A8: PINV-003 | B8: 2026-02-15 | C8: PO-003 | D8: V003 | E8: =INDEX('Vendor Master'!B6:B10,MATCH(D8,'Vendor Master'!A6:A10,0)) | F8: 15000 | G8: 2026-03-17 | H8: 15000 | I8: =F8-H8 | J8: Paid
A9: PINV-004 | B9: 2026-02-25 | C9: PO-004 | D9: V004 | E9: =INDEX('Vendor Master'!B6:B10,MATCH(D9,'Vendor Master'!A6:A10,0)) | F9: 25000 | G9: 2026-03-27 | H9: 0 | I9: =F9-H9 | J9: Outstanding
A10: PINV-005 | B10: 2026-03-10 | C10: PO-005 | D10: V005 | E10: =INDEX('Vendor Master'!B6:B10,MATCH(D10,'Vendor Master'!A6:A10,0)) | F10: 20000 | G10: 2026-04-24 | H10: 0 | I10: =F10-H10 | J10: Pending

Sheet Payment Register
A1: ABC Trading Pvt. Ltd.
A2: Payment Register
A5: Payment ID | B5: Payment Date | C5: Vendor ID | D5: Vendor Name | E5: Invoice No. | F5: Amount Paid | G5: Payment Method | H5: Reference
A6: PAY-001 | B6: 2026-01-30 | C6: V001 | D6: =INDEX('Vendor Master'!B6:B10,MATCH(C6,'Vendor Master'!A6:A10,0)) | E6: PINV-001 | F6: 20000 | G6: Bank Transfer | H6: UTR-001
A7: PAY-002 | B7: 2026-02-28 | C7: V002 | D7: =INDEX('Vendor Master'!B6:B10,MATCH(C7,'Vendor Master'!A6:A10,0)) | E7: PINV-002 | F7: 100000 | G7: Bank Transfer | H7: UTR-002
A8: PAY-003 | B8: 2026-03-20 | C8: V003 | D8: =INDEX('Vendor Master'!B6:B10,MATCH(C8,'Vendor Master'!A6:A10,0)) | E8: PINV-003 | F8: 15000 | G8: Bank Transfer | H8: UTR-003

Sheet 3-Way Match
A1: ABC Trading Pvt. Ltd.
A2: 3-Way Match Control
A3: Purchase Order → Receipt → Invoice validation
A5: Invoice No. | B5: PO No. | C5: PO Value | D5: Invoice Value | E5: Receipt Confirmed | F5: Price Match | G5: Quantity/Receipt Match | H5: Overall Match
A6: PINV-001 | B6: PO-001 | C6: 20000 | D6: 20000 | E6: Yes | F6: Yes | G6: Yes | H6: =IF(AND(E6="Yes",F6="Yes",G6="Yes",C6=D6),"Matched","Exception")
A7: PINV-002 | B7: PO-002 | C7: 150000 | D7: 150000 | E7: Yes | F7: Yes | G7: Yes | H7: =IF(AND(E7="Yes",F7="Yes",G7="Yes",C7=D7),"Matched","Exception")
A8: PINV-003 | B8: PO-003 | C8: 15000 | D8: 15000 | E8: Yes | F8: Yes | G8: Yes | H8: =IF(AND(E8="Yes",F8="Yes",G8="Yes",C8=D8),"Matched","Exception")
A9: PINV-004 | B9: PO-004 | C9: 25000 | D9: 25000 | E9: Yes | F9: Yes | G9: Yes | H9: =IF(AND(E9="Yes",F9="Yes",G9="Yes",C9=D9),"Matched","Exception")
A10: PINV-005 | B10: PO-005 | C10: 20000 | D10: 20000 | E10: No | F10: Yes | G10: No | H10: =IF(AND(E10="Yes",F10="Yes",G10="Yes",C10=D10),"Matched","Exception")

Sheet AP Ageing
A1: ABC Trading Pvt. Ltd.
A2: AP Ageing
A3: As at 31 March 2026
A5: Invoice No. | B5: Vendor | C5: Due Date | D5: Outstanding | E5: Days Outstanding | F5: Ageing Bucket
A6: PINV-002 | B6: =INDEX('AP Invoice Register'!E6:E10,MATCH(A6,'AP Invoice Register'!A6:A10,0)) | C6: 2026-03-08 | D6: 50000 | E6: 23 | F6: 0-30 Days
A7: PINV-004 | B7: =INDEX('AP Invoice Register'!E6:E10,MATCH(A7,'AP Invoice Register'!A6:A10,0)) | C7: 2026-03-27 | D7: 25000 | E7: 4 | F7: 0-30 Days
A8: PINV-005 | B8: =INDEX('AP Invoice Register'!E6:E10,MATCH(A8,'AP Invoice Register'!A6:A10,0)) | C8: 2026-04-24 | D8: 20000 | E8: 0 | F8: Not Yet Due

Sheet P2P Dashboard
A1: ABC Trading Pvt. Ltd.
A2: P2P Dashboard
A3: Procurement and payables overview
A5: Metric | B5: Result | C5: Category
A6: Total PO Value | B6: =SUM('Purchase Orders'!H6:H10) | C6: Procurement
A7: Total AP Invoiced | B7: =SUM('AP Invoice Register'!F6:F10) | C7: AP
A8: Total Paid | B8: =SUM('Payment Register'!F6:F8) | C8: Payments
A9: Outstanding AP | B9: =SUM('AP Invoice Register'!I6:I10) | C9: AP
A10: Matched Invoices | B10: =COUNTIF('3-Way Match'!H6:H10,"Matched") | C10: Control
A11: Exceptions | B11: =COUNTIF('3-Way Match'!H6:H10,"Exception") | C11: Control
A14: P2P MANAGEMENT OBSERVATIONS
A15: Purchase orders establish approved spend before supplier invoices are processed.
A16: The 3-way match validates purchase order value, receipt confirmation and invoice details.
A17: Payment records link supplier payments to invoice references for audit traceability.
A18: AP ageing highlights outstanding supplier balances requiring follow-up.
