Workbook

Sheet Customer Master
A1: ABC Trading Pvt. Ltd.
A2: Order-to-Cash (O2C) Portfolio
A3: Customer, order, invoice, collection and ageing workflow
A5: Customer ID | B5: Customer Name | C5: Customer Type | D5: Payment Terms | E5: Credit Limit
A6: C001 | B6: Alpha Retail | C6: Retail | D6: 30 Days | E6: 150000
A7: C002 | B7: Beta Stores | C7: Retail | D7: 30 Days | E7: 125000
A8: C003 | B8: City Mart | C8: Wholesale | D8: 45 Days | E8: 200000
A9: C004 | B9: Daily Needs | C9: Retail | D9: 30 Days | E9: 100000
A10: C005 | B10: Metro Traders | C10: Wholesale | D10: 45 Days | E10: 250000

Sheet Sales Orders
A1: ABC Trading Pvt. Ltd.
A2: Sales Orders
A5: Order ID | B5: Order Date | C5: Customer ID | D5: Customer Name | E5: Product | F5: Quantity | G5: Unit Price | H5: Order Value | I5: Status
A6: SO-001 | B6: 2026-01-05 | C6: C001 | D6: =INDEX('Customer Master'!B6:B10,MATCH(C6,'Customer Master'!A6:A10,0)) | E6: Laptop Accessories | F6: 10 | G6: 2500 | H6: =F6*G6 | I6: Invoiced
A7: SO-002 | B7: 2026-01-12 | C7: C003 | D7: =INDEX('Customer Master'!B6:B10,MATCH(C7,'Customer Master'!A6:A10,0)) | E7: Networking Equipment | F7: 5 | G7: 12000 | H7: =F7*G7 | I7: Invoiced
A8: SO-003 | B8: 2026-02-03 | C8: C002 | D8: =INDEX('Customer Master'!B6:B10,MATCH(C8,'Customer Master'!A6:A10,0)) | E8: Office Equipment | F8: 8 | G8: 5000 | H8: =F8*G8 | I8: Invoiced
A9: SO-004 | B9: 2026-02-18 | C9: C004 | D9: =INDEX('Customer Master'!B6:B10,MATCH(C9,'Customer Master'!A6:A10,0)) | E9: Printer Supplies | F9: 20 | G9: 1500 | H9: =F9*G9 | I9: Partially Paid
A10: SO-005 | B10: 2026-03-02 | C10: C005 | D10: =INDEX('Customer Master'!B6:B10,MATCH(C10,'Customer Master'!A6:A10,0)) | E10: IT Hardware | F10: 4 | G10: 15000 | H10: =F10*G10 | I10: Outstanding

Sheet Invoice Register
A1: ABC Trading Pvt. Ltd.
A2: Invoice Register
A5: Invoice No. | B5: Invoice Date | C5: Order ID | D5: Customer ID | E5: Customer Name | F5: Invoice Amount | G5: Due Date | H5: Amount Received | I5: Outstanding | J5: Status
A6: INV-001 | B6: 2026-01-10 | C6: SO-001 | D6: C001 | E6: =INDEX('Customer Master'!B6:B10,MATCH(D6,'Customer Master'!A6:A10,0)) | F6: 25000 | G6: 2026-02-09 | H6: 25000 | I6: =F6-H6 | J6: Paid
A7: INV-002 | B7: 2026-01-18 | C7: SO-002 | D7: C003 | E7: =INDEX('Customer Master'!B6:B10,MATCH(D7,'Customer Master'!A6:A10,0)) | F7: 60000 | G7: 2026-03-04 | H7: 40000 | I7: =F7-H7 | J7: Partially Paid
A8: INV-003 | B8: 2026-02-08 | C8: SO-003 | D8: C002 | E8: =INDEX('Customer Master'!B6:B10,MATCH(D8,'Customer Master'!A6:A10,0)) | F8: 40000 | G8: 2026-03-10 | H8: 40000 | I8: =F8-H8 | J8: Paid
A9: INV-004 | B9: 2026-02-22 | C9: SO-004 | D9: C004 | E9: =INDEX('Customer Master'!B6:B10,MATCH(D9,'Customer Master'!A6:A10,0)) | F9: 30000 | G9: 2026-03-24 | H9: 10000 | I9: =F9-H9 | J9: Partially Paid
A10: INV-005 | B10: 2026-03-05 | C10: SO-005 | D10: C005 | E10: =INDEX('Customer Master'!B6:B10,MATCH(D10,'Customer Master'!A6:A10,0)) | F10: 60000 | G10: 2026-04-19 | H10: 0 | I10: =F10-H10 | J10: Outstanding

Sheet Collection Register
A1: ABC Trading Pvt. Ltd.
A2: Collection Register
A5: Receipt ID | B5: Receipt Date | C5: Customer ID | D5: Customer Name | E5: Invoice No. | F5: Amount Received | G5: Payment Method | H5: Reference No.
A6: REC-001 | B6: 2026-01-25 | C6: C001 | D6: =INDEX('Customer Master'!B6:B10,MATCH(C6,'Customer Master'!A6:A10,0)) | E6: INV-001 | F6: 25000 | G6: Bank Transfer | H6: BT-001
A7: REC-002 | B7: 2026-02-25 | C7: C003 | D7: =INDEX('Customer Master'!B6:B10,MATCH(C7,'Customer Master'!A6:A10,0)) | E7: INV-002 | F7: 40000 | G7: Bank Transfer | H7: BT-002
A8: REC-003 | B8: 2026-03-15 | C8: C002 | D8: =INDEX('Customer Master'!B6:B10,MATCH(C8,'Customer Master'!A6:A10,0)) | E8: INV-003 | F8: 40000 | G8: Bank Transfer | H8: BT-003
A9: REC-004 | B9: 2026-03-28 | C9: C004 | D9: =INDEX('Customer Master'!B6:B10,MATCH(C9,'Customer Master'!A6:A10,0)) | E9: INV-004 | F9: 10000 | G9: Bank Transfer | H9: BT-004

Sheet O2C Ageing
A1: ABC Trading Pvt. Ltd.
A2: O2C Receivables Ageing
A3: As at 31 March 2026
A5: Invoice No. | B5: Customer | C5: Due Date | D5: Outstanding Amount | E5: Days Outstanding | F5: Ageing Bucket
A6: INV-002 | B6: =INDEX('Invoice Register'!E6:E10,MATCH(A6,'Invoice Register'!A6:A10,0)) | C6: 2026-03-04 | D6: 20000 | E6: 27 | F6: 0-30 Days
A7: INV-004 | B7: =INDEX('Invoice Register'!E6:E10,MATCH(A7,'Invoice Register'!A6:A10,0)) | C7: 2026-03-24 | D7: 20000 | E7: 7 | F7: 0-30 Days
A8: INV-005 | B8: =INDEX('Invoice Register'!E6:E10,MATCH(A8,'Invoice Register'!A6:A10,0)) | C8: 2026-04-19 | D8: 60000 | E8: 0 | F8: Not Yet Due

Sheet O2C Dashboard
A1: ABC Trading Pvt. Ltd.
A2: O2C Dashboard
A3: Key operational metrics
A5: Metric | B5: Result | C5: Category
A6: Total Orders | B6: =SUM('Sales Orders'!H6:H10) | C6: Order Value
A7: Total Invoiced | B7: =SUM('Invoice Register'!F6:F10) | C7: Billing
A8: Total Collected | B8: =SUM('Collection Register'!F6:F9) | C8: Collections
A9: Outstanding AR | B9: =SUM('Invoice Register'!I6:I10) | C9: Receivables
A10: Collection Rate | B10: =B8/B7 | C10: Collections
A13: O2C MANAGEMENT OBSERVATIONS
A14: Billing records link sales orders to customer invoices.
A15: Collections are tracked against individual invoices using receipt references.
A16: Outstanding receivables are separated into ageing buckets for follow-up.
A17: The dashboard summarizes billing, collection and outstanding receivable performance.
