Workbook

Sheet Ratio Analysis
A1: ABC Trading Pvt. Ltd.
A2: Financial Ratio Analysis
A3: For the Year Ended 31 March 2026
A5: FINANCIAL DATA
A6: Cash & Bank | B6: 490000
A7: Accounts Receivable | B7: 0
A8: Inventory | B8: 100000
A9: Current Assets | B9: =SUM(B6:B8) -> 590000
A10: Accounts Payable | B10: 100000
A11: Current Liabilities | B11: =B10 -> 100000
A12: Total Debt | B12: 100000
A13: Equity | B13: 500000
A14: Sales Revenue | B14: 75000
A15: Cost of Goods Sold | B15: 40000
A16: Gross Profit | B16: =B14-B15 -> 35000
A17: Net Profit | B17: =B16-10000 -> 25000
A19: LIQUIDITY RATIOS
A20: Current Ratio | B20: =B9/B11 -> 5.9 | C20: Current assets are 5.90 times current liabilities.
A21: Quick Ratio | B21: =(B9-B8)/B11 -> 4.9 | C21: Liquid assets are 4.90 times current liabilities after excluding inventory.
A22: Formula result
A23: PROFITABILITY RATIOS
A24: Gross Profit Margin | B24: =B16/B14 -> 0.46666667
A25: Net Profit Margin | B25: =B17/B14 -> 0.33333333
A26: Return on Equity | B26: =B17/B13 -> 0.05
A28: SOLVENCY RATIOS
A29: Debt-to-Equity Ratio | B29: 0.2 | C29: Debt relative to shareholders' equity
A31: EFFICIENCY RATIOS
A32: Inventory Turnover Ratio | B32: =B15/B8 -> 0.4 | C32: COGS relative to inventory
A35: KEY FINANCIAL RATIOS
A36: Current Ratio | B36: =B20 -> 5.9
A37: Quick Ratio | B37: =B21 -> 4.9
A38: Gross Profit Margin | B38: =B24 -> 0.46666667
A39: Net Profit Margin | B39: =B25 -> 0.33333333
A40: Return on Equity | B40: =B26 -> 0.05
A41: Debt-to-Equity Ratio | B41: =B29 -> 0.2
A42: Inventory Turnover | B42: =B32 -> 0.4

Sheet Dashboard
A1: ABC Trading Pvt. Ltd.
A2: Financial Ratio Dashboard
A3: For the Year Ended 31 March 2026
A5: Ratio | B5: Result | C5: Category
A6: Current Ratio | B6: ='Ratio Analysis'!B20 -> 5.9 | C6: Liquidity
A7: Quick Ratio | B7: ='Ratio Analysis'!B21 -> 4.9 | C7: Liquidity
A8: Gross Profit Margin | B8: ='Ratio Analysis'!B22 | C8: Profitability
A9: Net Profit Margin | B9: ='Ratio Analysis'!B23 | C9: Profitability
A10: Return on Equity | B10: ='Ratio Analysis'!B24 -> 0.46666667 | C10: Profitability
A11: Debt-to-Equity Ratio | B11: ='Ratio Analysis'!B25 -> 0.33333333 | C11: Solvency
A12: Inventory Turnover | B12: ='Ratio Analysis'!B26 -> 0.05 | C12: Efficiency
A15: KEY FINANCIAL INFORMATION
A16: Sales Revenue | B16: ='Ratio Analysis'!B14 -> 75000
A17: Gross Profit | B17: ='Ratio Analysis'!B16 -> 35000
A18: Net Profit | B18: ='Ratio Analysis'!B17 -> 25000
A19: Current Assets | B19: ='Ratio Analysis'!B9 -> 590000
A20: Current Liabilities | B20: ='Ratio Analysis'!B11 -> 100000
A21: Total Debt | B21: ='Ratio Analysis'!B12 -> 100000
A22: Equity | B22: ='Ratio Analysis'!B13 -> 500000
A25: FINANCIAL OBSERVATIONS
A26: Liquidity ratios indicate the relationship between current assets and current liabilities.
A27: Profitability ratios show the relationship between revenue, profit and equity.
A28: Debt-to-equity measures the level of debt relative to shareholders' equity.
A29: Inventory turnover compares cost of goods sold with the inventory balance.
